{"smp":"45-091B-011","barrio":"Caballito","direcciones":"AV. RIVADAVIA 4947/4949","estado":"ok","error":null,"flags":["esquina","contrafrente_obstruido","contrafrente_v3_no_validado"],"metodo":"frente_derivado","calle_frente":"RIVADAVIA AV.","centro":[-58.43514256958742,-34.617433015530764],"bbox":[-58.43525388488266,-34.61755521149656,-58.43503320894015,-34.61731440749166],"caras":{"frente":{"az":152.94831212378068,"orient":"SE","confianza":"media","en_validacion":false,"horas":{"3":{"2026-12-21":{"h":0.0,"iv":[]},"2026-03-21":{"h":0.0,"iv":[]},"2026-06-21":{"h":0.0,"iv":[]},"2026-09-21":{"h":0.0,"iv":[]}},"6":{"2026-12-21":{"h":0.0,"iv":[]},"2026-03-21":{"h":0.0,"iv":[]},"2026-06-21":{"h":0.0,"iv":[]},"2026-09-21":{"h":0.0,"iv":[]}},"9":{"2026-12-21":{"h":0.0,"iv":[]},"2026-03-21":{"h":0.0,"iv":[]},"2026-06-21":{"h":0.0,"iv":[]},"2026-09-21":{"h":0.0,"iv":[]}},"12":{"2026-12-21":{"h":0.0,"iv":[]},"2026-03-21":{"h":0.0,"iv":[]},"2026-06-21":{"h":0.0,"iv":[]},"2026-09-21":{"h":0.0,"iv":[]}},"15":{"2026-12-21":{"h":0.0,"iv":[]},"2026-03-21":{"h":0.0,"iv":[]},"2026-06-21":{"h":0.0,"iv":[]},"2026-09-21":{"h":0.0,"iv":[]}},"18":{"2026-12-21":{"h":0.0,"iv":[]},"2026-03-21":{"h":0.0,"iv":[]},"2026-06-21":{"h":0.0,"iv":[]},"2026-09-21":{"h":0.0,"iv":[]}},"21":{"2026-12-21":{"h":0.0,"iv":[]},"2026-03-21":{"h":0.0,"iv":[]},"2026-06-21":{"h":0.0,"iv":[]},"2026-09-21":{"h":0.0,"iv":[]}},"24":{"2026-12-21":{"h":0.0,"iv":[]},"2026-03-21":{"h":0.0,"iv":[]},"2026-06-21":{"h":0.0,"iv":[]},"2026-09-21":{"h":0.0,"iv":[]}},"27":{"2026-12-21":{"h":0.17,"iv":["11:30-11:40"]},"2026-03-21":{"h":0.0,"iv":[]},"2026-06-21":{"h":0.0,"iv":[]},"2026-09-21":{"h":0.0,"iv":[]}},"30":{"2026-12-21":{"h":0.17,"iv":["11:30-11:40"]},"2026-03-21":{"h":0.0,"iv":[]},"2026-06-21":{"h":0.0,"iv":[]},"2026-09-21":{"h":0.0,"iv":[]}}}},"contrafrente":{"az":332.9483121237807,"orient":"NO","confianza":"baja","en_validacion":true,"horas":{}}}}